{
  "sessionId": "sess_1773177949698",
  "planFile": ".switchboard\\plans\\feature_plan_20260311_082549_add_a_send_to_planner_button_to_airlock_tab.md",
  "topic": "Add a send to planner button to airlock tab",
  "createdAt": "2026-03-10T21:25:49.695Z",
  "events": [
    {
      "workflow": "initiate-plan",
      "timestamp": "2026-03-10T21:25:49.695Z",
      "action": "start"
    },
    {
      "workflow": "sidebar-review",
      "timestamp": "2026-03-11T18:24:16.954Z",
      "action": "start"
    },
    {
      "workflow": "coder",
      "timestamp": "2026-03-15T00:55:00.000Z",
      "action": "start"
    },
    {
      "workflow": "reviewer-pass",
      "timestamp": "2026-03-16T11:25:56.531Z",
      "action": "start"
    }
  ]
}