{
  "sessionId": "sess_1773727176216",
  "planFile": ".switchboard/plans/feature_plan_20260317_165936_delete_button_in_ticket_view_does_not_work.md",
  "topic": "Delete button in ticket view does not work",
  "createdAt": "2026-03-17T05:59:36.212Z",
  "events": [
    {
      "workflow": "initiate-plan",
      "timestamp": "2026-03-17T05:59:36.212Z",
      "action": "start"
    },
    {
      "workflow": "Improved plan",
      "timestamp": "2026-03-17T06:00:54.606Z",
      "action": "start"
    },
    {
      "workflow": "handoff",
      "timestamp": "2026-03-17T09:29:03.031Z",
      "action": "start"
    },
    {
      "workflow": "reviewer-pass",
      "timestamp": "2026-03-17T09:29:04.497Z",
      "action": "start"
    }
  ]
}